{
  "testament": "new",
  "title": "Novo Testamento",
  "subtitle": "A Vida de Cristo e a Igreja Primitiva",
  "period": "6 AC - 100 DC",
  "description": "Desde o nascimento de Jesus até o estabelecimento da Igreja cristã",
  "totalBooks": 27,
  "categories": [
    {
      "name": "Evangelhos",
      "books": ["Mateus", "Marcos", "Lucas", "João"],
      "description": "A vida e ministério de Jesus Cristo"
    },
    {
      "name": "História",
      "books": ["Atos"],
      "description": "A história da igreja primitiva"
    },
    {
      "name": "Epístolas Paulinas",
      "books": ["Romanos", "1 e 2 Coríntios", "Gálatas", "Efésios", "Filipenses", "Colossenses", "1 e 2 Tessalonicenses", "1 e 2 Timóteo", "Tito", "Filemom"],
      "description": "Cartas do apóstolo Paulo às igrejas"
    },
    {
      "name": "Epístolas Gerais",
      "books": ["Hebreus", "Tiago", "1 e 2 Pedro", "1, 2 e 3 João", "Judas"],
      "description": "Cartas dirigidas à igreja em geral"
    },
    {
      "name": "Profético",
      "books": ["Apocalipse"],
      "description": "Revelação sobre os últimos tempos"
    }
  ],
  "keyBooks": [
    {
      "id": "matthew",
      "name": "Mateus",
      "order": 40,
      "period": "60-70 DC",
      "author": "Mateus (Levi)",
      "chapters": 28,
      "theme": "Jesus, o Rei Prometido",
      "keyVerse": {
        "reference": "Mateus 1:23",
        "text": "Eis que a virgem conceberá e dará à luz um filho, e ele será chamado pelo nome de Emanuel."
      },
      "summary": "Apresenta Jesus como o Messias prometido, cumprimento das profecias do AT.",
      "keyEvents": [
        {
          "id": "birth_jesus",
          "title": "Nascimento de Jesus",
          "description": "Emanuel, Deus conosco, nasce de uma virgem em Belém",
          "verse": "Mateus 1:18-2:12",
          "significance": "Cumprimento das profecias messiânicas do AT",
          "archaeological": {
            "evidence": "Igreja da Natividade em Belém preserva tradição do local",
            "description": "Sítio arqueológico confirma ocupação de Belém no período",
            "image": "bethlehem-nativity.webp",
            "sources": ["Autoridade Palestina de Antiguidades", "UNESCO"]
          },
          "coordinates": {"lat": 31.7, "lng": 35.2, "label": "Belém - Nascimento de Jesus"}
        },
        {
          "id": "sermon_mount",
          "title": "Sermão do Monte",
          "description": "Jesus ensina as bem-aventuranças e princípios do Reino",
          "verse": "Mateus 5:1-7:29",
          "significance": "Constituição moral do Reino dos Céus",
          "archaeological": {
            "evidence": "Monte das Bem-aventuranças identificado próximo ao Mar da Galileia",
            "description": "Local tradicional com acústica natural ideal para ensino",
            "image": "mount-beatitudes.webp",
            "sources": ["Autoridade de Parques Israelenses", "Terra Santa"]
          },
          "coordinates": {"lat": 32.88, "lng": 35.55, "label": "Monte das Bem-aventuranças"}
        }
      ],
      "timeline": {"start": "60", "end": "70", "color": "#4169E1"}
    },
    {
      "id": "john",
      "name": "João",
      "order": 43,
      "period": "90-95 DC",
      "author": "João, o amado",
      "chapters": 21,
      "theme": "Jesus, o Filho de Deus",
      "keyVerse": {
        "reference": "João 20:31",
        "text": "Estes, porém, foram escritos para que creiais que Jesus é o Cristo, o Filho de Deus."
      },
      "summary": "Apresenta a divindade de Cristo através de sinais e discursos.",
      "keyEvents": [
        {
          "id": "water_wine",
          "title": "Água em Vinho",
          "description": "Primeiro milagre de Jesus transforma água em vinho em Caná",
          "verse": "João 2:1-11",
          "significance": "Manifesta a glória divina de Cristo",
          "archaeological": {
            "evidence": "Caná da Galileia identificada com vestígios do séc I",
            "description": "Sítio arqueológico preserva tradições do casamento bíblico",
            "image": "cana-wedding.webp",
            "sources": ["Universidade Franciscana", "Custódia da Terra Santa"]
          },
          "coordinates": {"lat": 32.75, "lng": 35.34, "label": "Caná da Galileia"}
        },
        {
          "id": "lazarus_resurrection",
          "title": "Ressurreição de Lázaro",
          "description": "Jesus ressuscita Lázaro após quatro dias morto",
          "verse": "João 11:1-44",
          "significance": "Demonstra poder sobre a morte, prefigura própria ressurreição",
          "archaeological": {
            "evidence": "Betânia escavada revela túmulos do período de Jesus",
            "description": "Túmulos em rocha do séc I confirmam práticas funerárias descritas",
            "image": "bethany-tomb.webp",
            "sources": ["Escuela Bíblica de Jerusalém", "Departamento de Antiguidades"]
          },
          "coordinates": {"lat": 31.77, "lng": 35.26, "label": "Betânia - Casa de Lázaro"}
        }
      ],
      "timeline": {"start": "90", "end": "95", "color": "#228B22"}
    },
    {
      "id": "acts",
      "name": "Atos",
      "order": 44,
      "period": "62-63 DC",
      "author": "Lucas",
      "chapters": 28,
      "theme": "Expansão da Igreja pelo Espírito Santo",
      "keyVerse": {
        "reference": "Atos 1:8",
        "text": "Mas recebereis poder ao descer sobre vós o Espírito Santo."
      },
      "summary": "História da igreja primitiva desde Pentecostes até Paulo em Roma.",
      "keyEvents": [
        {
          "id": "pentecost",
          "title": "Pentecostes",
          "description": "Descida do Espírito Santo marca início da Igreja",
          "verse": "Atos 2:1-31",
          "significance": "Nascimento da Igreja cristã universal",
          "archaeological": {
            "evidence": "Cenáculo tradicional preservado em Jerusalém",
            "description": "Local venerado desde os primeiros séculos como sala do Pentecostes",
            "image": "pentecost-upper-room.webp",
            "sources": ["Custódia Franciscana", "Patriarcado Armênio"]
          },
          "coordinates": {"lat": 31.77, "lng": 35.23, "label": "Cenáculo - Pentecostes"}
        },
        {
          "id": "paul_conversion",
          "title": "Conversão de Paulo",
          "description": "Saulo perseguidor torna-se Paulo apóstolo no caminho para Damasco",
          "verse": "Atos 9:1-19",
          "significance": "Transformação radical mostra poder do evangelho",
          "archaeological": {
            "evidence": "Via Romana para Damasco preservada arqueologicamente",
            "description": "Estrada do séc I mantém traçado da jornada de Paulo",
            "image": "damascus-road.webp",
            "sources": ["Museu Nacional de Damasco", "Instituto Arqueológico Alemão"]
          },
          "coordinates": {"lat": 33.31, "lng": 36.18, "label": "Estrada para Damasco"}
        }
      ],
      "timeline": {"start": "62", "end": "63", "color": "#FF6347"}
    },
    {
      "id": "revelation",
      "name": "Apocalipse",
      "order": 66,
      "period": "95-96 DC",
      "author": "João",
      "chapters": 22,
      "theme": "Vitória Final de Cristo",
      "keyVerse": {
        "reference": "Apocalipse 1:8",
        "text": "Eu sou o Alfa e Ômega, diz o Senhor Deus, aquele que é, que era e que há de vir."
      },
      "summary": "Revelação profética sobre o fim dos tempos e vitória definitiva de Cristo.",
      "keyEvents": [
        {
          "id": "christ_vision",
          "title": "Visão do Cristo Glorificado",
          "description": "João vê Jesus em Sua glória celestial em Patmos",
          "verse": "Apocalipse 1:9-20",
          "significance": "Revela a majestade divina do Cristo ressuscitado",
          "archaeological": {
            "evidence": "Ilha de Patmos identificada com tradições do exílio de João",
            "description": "Gruta da Apocalipse preserva local tradicional da revelação",
            "image": "patmos-apocalypse.webp",
            "sources": ["Monastério de São João", "Ministério Grego da Cultura"]
          },
          "coordinates": {"lat": 37.31, "lng": 26.55, "label": "Patmos - Ilha do Apocalipse"}
        }
      ],
      "timeline": {"start": "95", "end": "96", "color": "#9932CC"}
    }
  ]
}
